plexi/__init__.py
plexi/bitmap.py
plexi/color.py
plexi/coords.py
plexi/io_.py
plexi/images/logo.bmp
plexi-0.0.1.dist-info/METADATA
plexi-0.0.1.dist-info/WHEEL
plexi-0.0.1.dist-info/RECORD
