Metadata-Version: 2.3
Name: plexi
Version: 0.0.1
Summary: A module for working with 24 bit bitmap files
Author: Frederik Siegumfeldt
